games_on_python.py
games_on_python-0.1.0.dist-info/WHEEL
games_on_python-0.1.0.dist-info/METADATA
games_on_python-0.1.0.dist-info/RECORD
