Metadata-Version: 2.1
Name: games-on-python
Version: 0.1.0
Summary: 00101001
Author: Fab4key
Author-email: fab4key@gmail.com
Requires-Python: >=3.7,<4.0
Classifier: Programming Language :: Python :: 3
Classifier: Programming Language :: Python :: 3.7
Classifier: Programming Language :: Python :: 3.8
